basic_text_analyzer/__init__.py
basic_text_analyzer/analysis.py
basic_text_analyzer/stopwords.py
basic_text_analyzer_athar-0.0.1.dist-info/licenses/LICENSE.txt
basic_text_analyzer_athar-0.0.1.dist-info/METADATA
basic_text_analyzer_athar-0.0.1.dist-info/WHEEL
basic_text_analyzer_athar-0.0.1.dist-info/top_level.txt
basic_text_analyzer_athar-0.0.1.dist-info/RECORD
