Metadata-Version: 2.4
Name: basic_text_analyzer_athar
Version: 0.0.1
Summary: A simple NLP library for basic text analysis.
Author: Athar
Author-email: you@example.com
License: MIT
Classifier: Programming Language :: Python :: 3
Classifier: License :: OSI Approved :: MIT License
Classifier: Operating System :: OS Independent
Classifier: Topic :: Text Processing :: Linguistic
Requires-Python: >=3.8
License-File: LICENSE.txt
Dynamic: author
Dynamic: author-email
Dynamic: classifier
Dynamic: description
Dynamic: description-content-type
Dynamic: license
Dynamic: license-file
Dynamic: requires-python
Dynamic: summary
